setup.cfg
setup.py
test/tester.py
vizontele/_720pizle.py
vizontele/__init__.py
vizontele/base.py
vizontele/bin.py
vizontele/bin_movie.py
vizontele/crawler.py
vizontele/diziay.py
vizontele/dizibox.py
vizontele/dizilab.py
vizontele/dizimag.py
vizontele/dizimek.py
vizontele/dizipub.py
vizontele/dizist.py
vizontele/sezonlukdizi.py
vizontele.egg-info/PKG-INFO
vizontele.egg-info/SOURCES.txt
vizontele.egg-info/dependency_links.txt
vizontele.egg-info/entry_points.txt
vizontele.egg-info/requires.txt
vizontele.egg-info/top_level.txt