Metadata-Version: 1.1
Name: vizontele
Version: 2017.9.27
Summary: A tool to crawl and get sources of TV Shows from various Turkish web sites.
Home-page: https://github.com/halilozercan/vizontele
Author: Halil Ozercan
Author-email: halilozercan@gmail.com
License: UNKNOWN
Download-URL: https://github.com/halilozercan/vizontele/tarball/2017.09.27
Platform: UNKNOWN
